{"id": 700, "name": "Ha\u00dfberge", "ars": "096740000000", "population": 85371, "population_density": null, "gemeinden": {"096740210210": {"name": "Untermerzbach", "ars": "096740210210", "population": 1640, "population_density": 59.0}, "096745612111": {"name": "Aidhausen", "ars": "096745612111", "population": 1679, "population_density": 45.0}, "096745612120": {"name": "Bundorf", "ars": "096745612120", "population": 915, "population_density": 23.0}, "096745612121": {"name": "Burgpreppach", "ars": "096745612121", "population": 1370, "population_density": 35.0}, "096745610129": {"name": "Ebelsbach", "ars": "096745610129", "population": 3715, "population_density": 144.0}, "096740195195": {"name": "Sand a.Main", "ars": "096740195195", "population": 3109, "population_density": 253.0}, "096745610118": {"name": "Breitbrunn", "ars": "096745610118", "population": 1018, "population_density": 82.0}, "096740147147": {"name": "Ha\u00dffurt", "ars": "096740147147", "population": 13982, "population_density": 266.0}, "096745610201": {"name": "Stettfeld", "ars": "096745610201", "population": 1096, "population_density": 98.0}, "096745611190": {"name": "Rentweinsdorf", "ars": "096745611190", "population": 1575, "population_density": 64.0}, "096740221221": {"name": "Zeil a.Main", "ars": "096740221221", "population": 5631, "population_density": 158.0}, "096745611184": {"name": "Pfarrweisach", "ars": "096745611184", "population": 1490, "population_density": 52.0}, "096745612223": {"name": "Ermershausen", "ars": "096745612223", "population": 534, "population_density": 58.0}, "096745613219": {"name": "Wonfurt", "ars": "096745613219", "population": 1980, "population_density": 114.0}, "096740133133": {"name": "Eltmann", "ars": "096740133133", "population": 5538, "population_density": 136.0}, "096745613139": {"name": "G\u00e4dheim", "ars": "096745613139", "population": 1319, "population_density": 138.0}, "096745611130": {"name": "Ebern", "ars": "096745611130", "population": 7365, "population_density": 78.0}, "096745612149": {"name": "Hofheim i.UFr.", "ars": "096745612149", "population": 5203, "population_density": 92.0}, "096745612153": {"name": "Riedbach", "ars": "096745612153", "population": 1744, "population_density": 55.0}, "096740159159": {"name": "Oberaurach", "ars": "096740159159", "population": 4046, "population_density": 90.0}, "096745610160": {"name": "Kirchlauter", "ars": "096745610160", "population": 1327, "population_density": 78.0}, "096740163163": {"name": "Knetzgau", "ars": "096740163163", "population": 6680, "population_density": 108.0}, "096740164164": {"name": "K\u00f6nigsberg i.Bay.", "ars": "096740164164", "population": 3614, "population_density": 58.0}, "096740171171": {"name": "Maroldsweisach", "ars": "096740171171", "population": 3192, "population_density": 44.0}, "096745613180": {"name": "Theres", "ars": "096745613180", "population": 2772, "population_density": 90.0}, "096740187187": {"name": "Rauhenebrach", "ars": "096740187187", "population": 2837, "population_density": 46.0}}, "total_population": 85371}