{"id": 21, "name": "Nordrhein-Westfalen", "ars": "050000000000", "population": 18190422, "population_density": 1290.8358617518593, "landkreise": {"059150000000": {"name": "Hamm", "ars": "059150000000", "population": 180761, "population_density": 797.0}, "053340000000": {"name": "St\u00e4dteregion Aachen", "ars": "053340000000", "population": 564444, "population_density": 1221.6306524650809}, "051130000000": {"name": "Essen", "ars": "051130000000", "population": 586608, "population_density": 2789.0}, "055700000000": {"name": "Warendorf", "ars": "055700000000", "population": 283295, "population_density": 256.4551086323444}, "057740000000": {"name": "Paderborn", "ars": "057740000000", "population": 315400, "population_density": 523.4718801521876}, "051110000000": {"name": "D\u00fcsseldorf", "ars": "051110000000", "population": 631217, "population_density": 2903.0}, "053660000000": {"name": "Euskirchen", "ars": "053660000000", "population": 199828, "population_density": 247.94854074504076}, "053740000000": {"name": "Oberbergischer Kreis", "ars": "053740000000", "population": 275735, "population_density": 352.8051825121946}, "053620000000": {"name": "Rhein-Erft-Kreis", "ars": "053620000000", "population": 480989, "population_density": 864.8650634421992}, "055130000000": {"name": "Gelsenkirchen", "ars": "055130000000", "population": 265885, "population_density": 2534.0}, "059130000000": {"name": "Dortmund", "ars": "059130000000", "population": 595471, "population_density": 2121.0}, "051170000000": {"name": "M\u00fclheim an der Ruhr", "ars": "051170000000", "population": 173255, "population_density": 1898.0}, "057700000000": {"name": "Minden-L\u00fcbbecke", "ars": "057700000000", "population": 316196, "population_density": 478.49291262381564}, "051220000000": {"name": "Solingen", "ars": "051220000000", "population": 161545, "population_density": 1804.0}, "059540000000": {"name": "Ennepe-Ruhr-Kreis", "ars": "059540000000", "population": 324946, "population_density": 992.9656096705298}, "053820000000": {"name": "Rhein-Sieg-Kreis", "ars": "053820000000", "population": 610537, "population_density": 802.2871799743505}, "057660000000": {"name": "Lippe", "ars": "057660000000", "population": 349781, "population_density": 398.02954991837754}, "053160000000": {"name": "Leverkusen", "ars": "053160000000", "population": 166414, "population_density": 2110.0}, "059660000000": {"name": "Olpe", "ars": "059660000000", "population": 134332, "population_density": 216.189359199595}, "057110000000": {"name": "Bielefeld", "ars": "057110000000", "population": 338410, "population_density": 1307.0}, "051620000000": {"name": "Rhein-Kreis Neuss", "ars": "051620000000", "population": 458722, "population_density": 1020.8511407780748}, "053580000000": {"name": "D\u00fcren", "ars": "053580000000", "population": 272666, "population_density": 548.3886439820147}, "059700000000": {"name": "Siegen-Wittgenstein", "ars": "059700000000", "population": 276625, "population_density": 480.7241030275644}, "051660000000": {"name": "Viersen", "ars": "051660000000", "population": 302885, "population_density": 622.4559090083694}, "051700000000": {"name": "Wesel", "ars": "051700000000", "population": 467511, "population_density": 835.3781814759438}, "055660000000": {"name": "Steinfurt", "ars": "055660000000", "population": 459195, "population_density": 331.74384085192565}, "055620000000": {"name": "Recklinghausen", "ars": "055620000000", "population": 620646, "population_density": 1204.6590439638696}, "055540000000": {"name": "Borken", "ars": "055540000000", "population": 381627, "population_density": 352.3790350263477}, "051580000000": {"name": "Mettmann", "ars": "051580000000", "population": 490251, "population_density": 1328.7888326591888}, "051540000000": {"name": "Kleve", "ars": "051540000000", "population": 321491, "population_density": 310.0584588682109}, "051120000000": {"name": "Duisburg", "ars": "051120000000", "population": 503707, "population_density": 2163.0}, "053700000000": {"name": "Heinsberg", "ars": "053700000000", "population": 262656, "population_density": 476.91886726364527}, "059580000000": {"name": "Hochsauerlandkreis", "ars": "059580000000", "population": 261774, "population_density": 189.61726527462622}, "051190000000": {"name": "Oberhausen", "ars": "051190000000", "population": 211099, "population_density": 2738.0}, "059740000000": {"name": "Soest", "ars": "059740000000", "population": 306674, "population_density": 364.72561090930435}, "051200000000": {"name": "Remscheid", "ars": "051200000000", "population": 112970, "population_density": 1516.0}, "053150000000": {"name": "K\u00f6ln", "ars": "053150000000", "population": 1087353, "population_density": 2685.0}, "059140000000": {"name": "Hagen", "ars": "059140000000", "population": 190490, "population_density": 1187.0}, "053140000000": {"name": "Bonn", "ars": "053140000000", "population": 335789, "population_density": 2380.0}, "051140000000": {"name": "Krefeld", "ars": "051140000000", "population": 228550, "population_density": 1659.0}, "059160000000": {"name": "Herne", "ars": "059160000000", "population": 157896, "population_density": 3071.0}, "055150000000": {"name": "M\u00fcnster", "ars": "055150000000", "population": 322904, "population_density": 1065.0}, "057620000000": {"name": "H\u00f6xter", "ars": "057620000000", "population": 141883, "population_density": 134.741914112332}, "055120000000": {"name": "Bottrop", "ars": "055120000000", "population": 118705, "population_density": 1180.0}, "055580000000": {"name": "Coesfeld", "ars": "055580000000", "population": 226160, "population_density": 216.5518084541917}, "051160000000": {"name": "M\u00f6nchengladbach", "ars": "051160000000", "population": 268943, "population_density": 1578.0}, "059110000000": {"name": "Bochum", "ars": "059110000000", "population": 366385, "population_density": 2515.0}, "057540000000": {"name": "G\u00fctersloh", "ars": "057540000000", "population": 372938, "population_density": 506.9868074586124}, "051240000000": {"name": "Wuppertal", "ars": "051240000000", "population": 358938, "population_density": 2132.0}, "053780000000": {"name": "Rheinisch-Bergischer Kreis", "ars": "053780000000", "population": 286778, "population_density": 866.0317737064906}, "059620000000": {"name": "M\u00e4rkischer Kreis", "ars": "059620000000", "population": 408579, "population_density": 531.3711766879844}, "059780000000": {"name": "Unna", "ars": "059780000000", "population": 399447, "population_density": 903.6642383094628}, "057580000000": {"name": "Herford", "ars": "057580000000", "population": 253136, "population_density": 660.251287845269}}, "total_population": 18190422}