{"id": 476, "name": "Mettmann", "ars": "051580000000", "population": 490251, "population_density": 1328.7888326591888, "gemeinden": {"051580020020": {"name": "Langenfeld (Rhld.)", "ars": "051580020020", "population": 59908, "population_density": 1456.0}, "051580004004": {"name": "Erkrath", "ars": "051580004004", "population": 43801, "population_density": 1630.0}, "051580012012": {"name": "Heiligenhaus", "ars": "051580012012", "population": 26590, "population_density": 966.0}, "051580026026": {"name": "Monheim am Rhein", "ars": "051580026026", "population": 43524, "population_density": 1888.0}, "051580036036": {"name": "W\u00fclfrath", "ars": "051580036036", "population": 21009, "population_density": 651.0}, "051580008008": {"name": "Haan", "ars": "051580008008", "population": 30558, "population_density": 1263.0}, "051580016016": {"name": "Hilden", "ars": "051580016016", "population": 55689, "population_density": 2146.0}, "051580024024": {"name": "Mettmann", "ars": "051580024024", "population": 39197, "population_density": 921.0}, "051580028028": {"name": "Ratingen", "ars": "051580028028", "population": 87513, "population_density": 986.0}, "051580032032": {"name": "Velbert", "ars": "051580032032", "population": 82462, "population_density": 1101.0}}, "total_population": 490251}