{"id": 627, "name": "Alt\u00f6tting", "ars": "091710000000", "population": 114459, "population_density": 415.872548248718, "gemeinden": {"091710111111": {"name": "Alt\u00f6tting", "ars": "091710111111", "population": 13172, "population_density": 571.0}, "091710112112": {"name": "Burghausen", "ars": "091710112112", "population": 19494, "population_density": 984.0}, "091710113113": {"name": "Burgkirchen a.d.Alz", "ars": "091710113113", "population": 11008, "population_density": 238.0}, "091715104115": {"name": "Erlbach", "ars": "091715104115", "population": 1174, "population_density": 42.0}, "091715102116": {"name": "Feichten a.d.Alz", "ars": "091715102116", "population": 1342, "population_density": 75.0}, "091715102119": {"name": "Halsbach", "ars": "091715102119", "population": 1083, "population_density": 49.0}, "091715106121": {"name": "Kastl", "ars": "091715106121", "population": 2814, "population_density": 102.0}, "091715102122": {"name": "Kirchweidach", "ars": "091715102122", "population": 2836, "population_density": 141.0}, "091715103123": {"name": "Marktl", "ars": "091715103123", "population": 2826, "population_density": 102.0}, "091715101124": {"name": "Mehring", "ars": "091715101124", "population": 2416, "population_density": 103.0}, "091710125125": {"name": "Neu\u00f6tting", "ars": "091710125125", "population": 9062, "population_density": 248.0}, "091710127127": {"name": "Pleiskirchen", "ars": "091710127127", "population": 2464, "population_density": 47.0}, "091715104129": {"name": "Reischach", "ars": "091715104129", "population": 2706, "population_density": 95.0}, "091710133133": {"name": "T\u00fc\u00dfling", "ars": "091710133133", "population": 3315, "population_density": 170.0}, "091715106135": {"name": "Unterneukirchen", "ars": "091715106135", "population": 3463, "population_density": 149.0}, "091710137137": {"name": "Winh\u00f6ring", "ars": "091710137137", "population": 4856, "population_density": 197.0}, "091715101114": {"name": "Emmerting", "ars": "091715101114", "population": 4254, "population_density": 302.0}, "091715103130": {"name": "Stammham", "ars": "091715103130", "population": 1019, "population_density": 179.0}, "091710117117": {"name": "Garching a.d.Alz", "ars": "091710117117", "population": 8837, "population_density": 342.0}, "091710118118": {"name": "Haiming", "ars": "091710118118", "population": 2527, "population_density": 88.0}, "091710132132": {"name": "T\u00f6ging a.Inn", "ars": "091710132132", "population": 9560, "population_density": 700.0}, "091710131131": {"name": "Teising", "ars": "091710131131", "population": 1806, "population_density": 336.0}, "091715102134": {"name": "Tyrlaching", "ars": "091715102134", "population": 1093, "population_density": 53.0}, "091715104126": {"name": "Perach", "ars": "091715104126", "population": 1332, "population_density": 94.0}}, "total_population": 114459}